pyjags_jw-0.3.1.dist-info/RECORD
pyjags_jw-0.3.1.dist-info/WHEEL
pyjags_jw-0.3.1.dist-info/METADATA
pyjags_jw-0.3.1.dist-info/licenses/LICENSE
pyjags/console.cpython-311-darwin.so
pyjags/_version.py
pyjags/chain_utilities.py
pyjags/io.py
pyjags/__init__.py
pyjags/incremental_sampling.py
pyjags/model.py
pyjags/dic.py
pyjags/progressbar.py
pyjags/console.cc
pyjags/modules.py
pyjags/_vendor/jags/lib/libjags.4.dylib
pyjags/_vendor/jags/lib/libjrmath.dylib
pyjags/_vendor/jags/lib/libjags.dylib
pyjags/_vendor/jags/lib/libjrmath.0.dylib
pyjags/_vendor/jags/lib/JAGS/modules-4/bugs.so
pyjags/_vendor/jags/lib/JAGS/modules-4/msm.so
pyjags/_vendor/jags/lib/JAGS/modules-4/dic.so
pyjags/_vendor/jags/lib/JAGS/modules-4/mix.la
pyjags/_vendor/jags/lib/JAGS/modules-4/dic.la
pyjags/_vendor/jags/lib/JAGS/modules-4/mix.so
pyjags/_vendor/jags/lib/JAGS/modules-4/bugs.la
pyjags/_vendor/jags/lib/JAGS/modules-4/msm.la
pyjags/_vendor/jags/lib/JAGS/modules-4/glm.so
pyjags/_vendor/jags/lib/JAGS/modules-4/basemod.so
pyjags/_vendor/jags/lib/JAGS/modules-4/lecuyer.la
pyjags/_vendor/jags/lib/JAGS/modules-4/glm.la
pyjags/_vendor/jags/lib/JAGS/modules-4/basemod.la
pyjags/_vendor/jags/lib/JAGS/modules-4/lecuyer.so
pyjags/.dylibs/libjags.4.dylib
pyjags/.dylibs/libopenblasp-r0.3.30.dylib
pyjags/.dylibs/libgfortran.5.dylib
pyjags/.dylibs/libjrmath.0.dylib
pyjags/.dylibs/libquadmath.0.dylib
pyjags/.dylibs/libgcc_s.1.1.dylib
pyjags/.dylibs/libgomp.1.dylib
