Metadata-Version: 2.2
Name: pyjags-jw
Version: 0.3.1
Summary: Python bindings for JAGS (modernized build so that everything 'just works' (JW)).
Author-Email: Scout Jarman <scoutjarman@yahoo.com>
License: GPL-2.0-only
Classifier: Development Status :: 4 - Beta
Classifier: Intended Audience :: Science/Research
Classifier: License :: OSI Approved :: GNU General Public License v2 (GPLv2)
Classifier: Programming Language :: Python :: 3
Classifier: Programming Language :: Python :: 3 :: Only
Classifier: Programming Language :: Python :: 3.11
Classifier: Programming Language :: Python :: 3.12
Classifier: Programming Language :: Python :: 3.13
Classifier: Programming Language :: C++
Classifier: Operating System :: POSIX :: Linux
Classifier: Topic :: Scientific/Engineering
Project-URL: Homepage, https://github.com/scoutiii/pyjags_JW
Project-URL: Issues, https://github.com/scoutiii/pyjags_JW/issues
Requires-Python: >=3.11
Requires-Dist: numpy>=1.23
Requires-Dist: arviz>=0.15
Requires-Dist: h5py>=3.8
Requires-Dist: pandas>=2.1
Requires-Dist: xarray>=2023.7.0
